qtinteract.py
qtinteract-0.2.dist-info/METADATA
qtinteract-0.2.dist-info/WHEEL
qtinteract-0.2.dist-info/top_level.txt
qtinteract-0.2.dist-info/RECORD
